<?xml version="1.0" encoding="utf-8" ?>
<dwsync>
<file name="VIJU_Fall_Large.jpg" local="129608064000000000" remote="129961891800000000" testing="0" />
<file name="VIJU_Fall_small.jpg" local="129608064000000000" remote="129961891800000000" testing="0" />
<file name="VIJU_Spring_large.jpg" local="129608064000000000" remote="129961891800000000" testing="0" />
<file name="VIJU_Spring_large_out.jpg" local="129608064000000000" remote="129961891800000000" testing="0" />
<file name="VIJU_Spring_small.jpg" local="129608064000000000" remote="129961891800000000" testing="0" />
<file name="VIJU_Spring_small_out.jpg" local="129608064000000000" remote="129961891800000000" testing="0" />
<file name="VIPR1_large.jpg" local="129608064000000000" remote="129961891800000000" testing="0" />
<file name="VIPR1_small.jpg" local="129608064000000000" remote="129961891800000000" testing="0" />
<file name="VIacML2_large.jpg" local="129608064000000000" remote="129961891800000000" testing="0" />
<file name="VIacML2_small.jpg" local="129608064000000000" remote="129961891800000000" testing="0" />
<file name="VIbuMO2_large.jpg" local="129608064000000000" remote="129961891800000000" testing="0" />
<file name="VIbuMO2_small.jpg" local="129608064000000000" remote="129961891800000000" testing="0" />
<file name="VIopST1_large.jpg" local="129608064000000000" remote="130084694400000000" testing="0" />
<file name="VItoSH1_large.jpg" local="129608064000000000" remote="129961891800000000" testing="0" />
<file name="VItoSH1_large_out.jpg" local="129608064000000000" remote="129961891800000000" testing="0" />
<file name="VItoSH1_small.jpg" local="129608064000000000" remote="129961891800000000" testing="0" />
<file name="VItoSH1_small_out.jpg" local="129608064000000000" remote="129961891800000000" testing="0" />
<file name="VItoSH2_large.jpg" local="129608064000000000" remote="129961891800000000" testing="0" />
<file name="VItoSH2_large_out.jpg" local="129608064000000000" remote="129961891800000000" testing="0" />
<file name="VItoSH2_small.jpg" local="129608064000000000" remote="129961891800000000" testing="0" />
<file name="VItoSH2_small_out.jpg" local="129608064000000000" remote="129961891800000000" testing="0" />
<file name="VIplNP_large.jpg" local="129815205443105469" remote="129961891800000000" testing="0" />
<file name="VIplNP_small.jpg" local="129815205443105469" remote="129961891800000000" testing="0" />
<file name="VIplNP1.jpg" local="129822961217187500" remote="129961891800000000" testing="0" />
<file name="VIplNP3.jpg" local="129822963823437500" remote="129961891800000000" testing="0" />
<file name="Viburnum.Mohawk.JPG" local="129896178651367188" remote="129961891800000000" testing="0" />
<file name="VIpr2.jpg" local="129957586007031250" remote="129961891800000000" testing="0" />
<file name="VIpr3.jpg" local="129957590979687500" remote="129961891800000000" testing="0" />
<file name="VIopST2.jpg" local="130084636973281250" remote="130084694400000000" testing="0" />
</dwsync>